[
  {
    "id": 1,
    "event_name": "The Battleground 2K22",
    "event_start": "12/3/2022 18:00",
    "event_end": "3/27/2022",
    "event_venue_name": "Dickies Arena",
    "event_street": "1911 Montgomery Street",
    "event_city": "Fort Worth",
    "event_state": "TX",
    "event_pic": "https://epfccsgtnbatrzapewjg.supabase.co/storage/v1/object/public/private/static/events/1/banner.png",
    "event_pic_2": "https://epfccsgtnbatrzapewjg.supabase.co/storage/v1/object/public/private/static/events/1/banner2.png",
    "description": ""
  }
]